easy_stream/__init__.py
easy_stream/concurrent_lib/__init__.py
easy_stream/concurrent_lib/process_runner.py
easy_stream/concurrent_lib/runner.py
easy_stream/concurrent_lib/simple_runner.py
easy_stream/concurrent_lib/task/__init__.py
easy_stream/concurrent_lib/task/group.py
easy_stream/concurrent_lib/task/parallel.py
easy_stream/concurrent_lib/task/serial.py
easy_stream/concurrent_lib/task/task.py
easy_stream/concurrent_lib/thread_runner.py
easy_stream/stream_lib/__init__.py
easy_stream/stream_lib/df_stream.py
easy_stream/stream_lib/new_stream.py
easy_stream/stream_lib/new_stream_op.py
easy_stream/stream_lib/stream.py
easy_stream/stream_lib/stream_op.py
easy_stream/task_lib/__init__.py
easy_stream/task_lib/context.py
easy_stream/task_lib/locator.py
easy_stream/task_lib/locators/__init__.py
easy_stream/task_lib/locators/locator.py
easy_stream/task_lib/locators/posix.py
easy_stream/task_lib/locators/step.py
easy_stream/task_lib/step.py
easy_stream/task_lib/task_infos.py
easy_stream/task_lib/task_logger.py
easy_stream/task_lib/tasks/__init__.py
easy_stream/task_lib/tasks/base_task.py
easy_stream/task_lib/tasks/clean.py
easy_stream/task_lib/tasks/groups/__init__.py
easy_stream/task_lib/tasks/groups/group.py
easy_stream/task_lib/tasks/groups/parallel.py
easy_stream/task_lib/tasks/groups/sequential.py
easy_stream/task_lib/tasks/name.py
easy_stream/task_lib/tasks/place_holder.py
easy_stream/task_lib/tasks/prepare.py
easy_stream/task_lib/tasks/skip.py
easy_stream/task_lib/tasks/status.py
easy_stream/task_lib/utils/__init__.py
easy_stream/task_lib/utils/copy.py
easy_stream/task_lib/utils/sleep.py
easy_stream-0.1.0.dist-info/LICENSE
easy_stream-0.1.0.dist-info/METADATA
easy_stream-0.1.0.dist-info/WHEEL
easy_stream-0.1.0.dist-info/RECORD
