Metadata-Version: 2.1
Name: easy-stream
Version: 0.1.0
Summary: Task orchestration library
Home-page: https://github.com/flegac/easy-kit
License: MIT
Author: flegac
Author-email: florent.legac@gmail.com
Requires-Python: >=3.8,<4.0
Classifier: License :: OSI Approved :: MIT License
Classifier: Operating System :: OS Independent
Classifier: Programming Language :: Python :: 3
Classifier: Programming Language :: Python :: 3.8
Classifier: Programming Language :: Python :: 3.9
Classifier: Programming Language :: Python :: 3.10
Classifier: Programming Language :: Python :: 3.11
Classifier: Programming Language :: Python :: 3.12
Project-URL: Repository, https://github.com/flegac/easy-kit
